Metadata-Version: 2.1
Name: django-chunked-iterator
Version: 0.6.1
Summary: Iterates Django querysets by chunks, saving memory and allows to start faster.
Home-page: https://github.com/homm/django-chunked-iterator
Author: Alexander Karpinsky
Author-email: homm86@gmail.com
License: UNKNOWN
Platform: UNKNOWN
